{
    "display": {
        "borderless-fullscreen": false,
        "resolution": {
            "width": 800,
            "height": 600
        },
        "fps-limit": 60,
        "vsync": true
    },
    "debug": {
        "window-title": "Chity Shimulator",
        "world-name": "collision_test.tmx",
        "human-skin": "Business Man",
        "zoom": 1,
        "reload-config": true,
        "movement": {
            "stop-decay": 8,
            "force": 80,
            "max-speed": 40
        },
        "start-pos": {
            "x": 0,
            "y": 0
        }
    },
    "resources": {
        "root": "res",
        "entities": {
            "root": "entities",
            "config": "entities.json",
            "sprites": "sprites",
            "controller-arrow": "/misc/controller_arrow.png"
        },
        "world": {
            "root": "world",
            "tileset": "tileset.png"
        },
        "misc": {
            "root": "misc",
            "font": "font.ttf",
            "icon": "icon.png"
        }
    }
}